{
  "schemaVersion": 1,
  "plugins": [
    {
      "id": "com.twilightecho.provider.bilibili",
      "name": "Bilibili Favorites Provider",
      "version": "0.1.1",
      "description": "Play audio from videos in the signed-in user's Bilibili favorite folders.",
      "author": "Twilight Echo",
      "license": "Apache-2.0",
      "type": [
        "provider",
        "ui"
      ],
      "main": "index.mjs",
      "engines": {
        "twilightEcho": ">=0.20.0"
      },
      "apiVersion": 1,
      "permissions": [
        "network",
        "settings",
        "ui:inject"
      ],
      "sourceUrl": "packages/com.twilightecho.provider.bilibili-0.1.1.tep",
      "checksumSha256": "eeb75c557359fab1a89a118311bbf223af2ff877dc97f0d2888a7e9eeddf1901",
      "repository": "https://github.com/asenyarzc-cpu/Twilight-Echo-plugins",
      "homepage": "https://github.com/asenyarzc-cpu/Twilight-Echo-plugins",
      "tags": [
        "provider",
        "ui",
        "bilibili"
      ],
      "verified": true
    }
  ]
}
